CHANGES.rst
CODE_OF_CONDUCT.md
CONTRIBUTING.md
LICENSE
README.rst
setup.cfg
setup.py
src/senaite/__init__.py
src/senaite.storage.egg-info/PKG-INFO
src/senaite.storage.egg-info/SOURCES.txt
src/senaite.storage.egg-info/dependency_links.txt
src/senaite.storage.egg-info/entry_points.txt
src/senaite.storage.egg-info/namespace_packages.txt
src/senaite.storage.egg-info/not-zip-safe
src/senaite.storage.egg-info/requires.txt
src/senaite.storage.egg-info/top_level.txt
src/senaite/storage/__init__.py
src/senaite/storage/api.py
src/senaite/storage/catalog.py
src/senaite/storage/config.py
src/senaite/storage/configure.zcml
src/senaite/storage/interfaces.py
src/senaite/storage/permissions.py
src/senaite/storage/permissions.zcml
src/senaite/storage/setuphandlers.py
src/senaite/storage/adapters/__init__.py
src/senaite/storage/adapters/breadcrumbs.py
src/senaite/storage/adapters/configure.zcml
src/senaite/storage/adapters/listing.py
src/senaite/storage/adapters/utilization.py
src/senaite/storage/browser/__init__.py
src/senaite/storage/browser/configure.zcml
src/senaite/storage/browser/controlpanel.py
src/senaite/storage/browser/container/__init__.py
src/senaite/storage/browser/container/configure.zcml
src/senaite/storage/browser/container/move_container.py
src/senaite/storage/browser/container/samples.py
src/senaite/storage/browser/container/store_container.py
src/senaite/storage/browser/container/store_samples.py
src/senaite/storage/browser/container/view.py
src/senaite/storage/browser/container/templates/move_container.pt
src/senaite/storage/browser/container/templates/store_container.pt
src/senaite/storage/browser/container/templates/store_samples.pt
src/senaite/storage/browser/facility/__init__.py
src/senaite/storage/browser/facility/configure.zcml
src/senaite/storage/browser/facility/view.py
src/senaite/storage/browser/position/__init__.py
src/senaite/storage/browser/position/configure.zcml
src/senaite/storage/browser/position/view.py
src/senaite/storage/browser/static/resources.pt
src/senaite/storage/browser/static/assets/icons/storage-container.svg
src/senaite/storage/browser/static/assets/icons/storage-facility.svg
src/senaite/storage/browser/static/assets/icons/storage-position.svg
src/senaite/storage/browser/static/assets/icons/storage-sample-container.svg
src/senaite/storage/browser/static/assets/icons/storage.svg
