Metadata-Version: 2.1
Name: senaite.storage
Version: 2.6.0
Summary: Sample storage add-on for SENAITE
Home-page: https://github.com/senaite/senaite.storage
Author: RIDING BYTES & NARALABS
Author-email: senaite@senaite.com
License: GPLv2
Keywords: senaite,lims,opensource
Platform: UNKNOWN
Classifier: Framework :: Plone
Classifier: Framework :: Zope2
Classifier: Programming Language :: Python
Classifier: License :: OSI Approved :: GNU General Public License v2 (GPLv2)
Provides-Extra: test
